jinja2_copier_extension/__init__.py
jinja2_copier_extension/_utils.py
jinja2_copier_extension/extension.py
jinja2_copier_extension/py.typed
jinja2_copier_extension/_filters/__init__.py
jinja2_copier_extension/_filters/base64.py
jinja2_copier_extension/_filters/datetime.py
jinja2_copier_extension/_filters/hash.py
jinja2_copier_extension/_filters/json.py
jinja2_copier_extension/_filters/path.py
jinja2_copier_extension/_filters/random.py
jinja2_copier_extension/_filters/regex.py
jinja2_copier_extension/_filters/shell.py
jinja2_copier_extension/_filters/types.py
jinja2_copier_extension/_filters/utils.py
jinja2_copier_extension/_filters/uuid.py
jinja2_copier_extension/_filters/yaml.py
jinja2_copier_extension-0.1.0.dist-info/METADATA
jinja2_copier_extension-0.1.0.dist-info/WHEEL
jinja2_copier_extension-0.1.0.dist-info/licenses/LICENSE
jinja2_copier_extension-0.1.0.dist-info/RECORD
