Metadata-Version: 2.4
Name: jinja2-copier-extension
Version: 0.1.0
Summary: Copier's built-in Jinja2 extension, inspired by Ansible, outsourced for you
Project-URL: Homepage, https://github.com/copier-org/jinja2-copier-extension
Project-URL: Repository, https://github.com/copier-org/jinja2-copier-extension
Author-email: Sigurd Spieckermann <sigurd.spieckermann@gmail.com>
License: MIT
License-File: LICENSE
Keywords: copier,extension,filters,jinja,jinja2
Classifier: Development Status :: 4 - Beta
Classifier: Intended Audience :: Developers
Classifier: License :: OSI Approved :: MIT License
Classifier: Operating System :: OS Independent
Classifier: Programming Language :: Python
Classifier: Programming Language :: Python :: 3
Classifier: Programming Language :: Python :: 3.9
Classifier: Programming Language :: Python :: 3.10
Classifier: Programming Language :: Python :: 3.11
Classifier: Programming Language :: Python :: 3.12
Classifier: Programming Language :: Python :: 3.13
Requires-Python: >=3.9
Requires-Dist: jinja2>=3.0.0
Provides-Extra: yaml
Requires-Dist: pyyaml>=6.0.0; extra == 'yaml'
